dspy_hub/__init__.py
dspy_hub/__main__.py
dspy_hub/cli.py
dspy_hub/config.py
dspy_hub/exceptions.py
dspy_hub/hub.py
dspy_hub/installer.py
dspy_hub/repository.py
dspy_hub/sample_registry/index.json
dspy_hub/sample_registry/packages/dspy-team/people-extractor/optimized_program.json
dspy_hub-0.1.1.dist-info/METADATA
dspy_hub-0.1.1.dist-info/WHEEL
dspy_hub-0.1.1.dist-info/entry_points.txt
dspy_hub-0.1.1.dist-info/top_level.txt
dspy_hub-0.1.1.dist-info/RECORD
