Metadata-Version: 2.4
Name: dspy-hub
Version: 0.1.1
Summary: DSPy Hub CLI and SDK for browsing and publishing DSPy programs
Author-email: Kevin Madura <hello@kmad.ai>
Requires-Python: >=3.10
